blopic/__init__.py
blopic/__main__.py
blopic/_version.py
blopic/entrypoint.py
blopic-2.1.1.dist-info/LICENSE
blopic-2.1.1.dist-info/METADATA
blopic-2.1.1.dist-info/WHEEL
blopic-2.1.1.dist-info/entry_points.txt
blopic-2.1.1.dist-info/top_level.txt
blopic-2.1.1.dist-info/RECORD
