Metadata-Version: 2.1
Name: blopic
Version: 2.1.1
Summary: Tool to convert and resize image for blog post.
Author: romaiiiiinnn
License: MIT
Project-URL: Homepage, https://gitlab.com/romaiiiinnn/blog-post-image-converter
Project-URL: Bug Tracker, https://gitlab.com/romaiiiinnn/blog-post-image-converter/-/issues
Classifier: Programming Language :: Python :: 3
Classifier: Environment :: Console
Classifier: License :: OSI Approved :: MIT License
Classifier: Operating System :: OS Independent
Classifier: Topic :: Utilities
Requires-Python: >=3.12
License-File: LICENSE
Requires-Dist: click ==8.1.7
Requires-Dist: Pillow ==10.2.0
